flatten_iterables/__about__.py
flatten_iterables/__init__.py
flatten_iterables/fi.py
flatten_iterables-1.0.3.dist-info/METADATA
flatten_iterables-1.0.3.dist-info/WHEEL
flatten_iterables-1.0.3.dist-info/licenses/LICENSE
flatten_iterables-1.0.3.dist-info/RECORD
