Metadata-Version: 2.4
Name: flatten_iterables
Version: 1.0.3
Summary: Flatten iterables and mappings into a dictionary of reference paths and values.
Project-URL: Homepage, https://github.com/faranalytics/flatten_iterables.git
Project-URL: Bug Tracker, https://github.com/faranalytics/flatten_iterables/issues
Author-email: Adam Patterson <adam@farar.net>
License-File: LICENSE
Classifier: License :: OSI Approved :: MIT License
Classifier: Operating System :: OS Independent
Classifier: Programming Language :: Python :: 3
Requires-Python: >=3.8
